[
  {
    "source": "ArXiv Paper",
    "title": "Discovering Hidden Gems in Model Repositories",
    "url": "http://arxiv.org/abs/2601.22157v1",
    "type": "research"
  },
  {
    "source": "ArXiv Paper",
    "title": "Hybrid Linear Attention Done Right: Efficient Distillation and Effective Architectures for Extremely Long Contexts",
    "url": "http://arxiv.org/abs/2601.22156v1",
    "type": "research"
  },
  {
    "source": "ArXiv Paper",
    "title": "Late Breaking Results: Conversion of Neural Networks into Logic Flows for Edge Computing",
    "url": "http://arxiv.org/abs/2601.22151v1",
    "type": "research"
  },
  {
    "source": "ArXiv Paper",
    "title": "FineInstructions: Scaling Synthetic Instructions to Pre-Training Scale",
    "url": "http://arxiv.org/abs/2601.22146v1",
    "type": "research"
  },
  {
    "source": "ArXiv Paper",
    "title": "Routing the Lottery: Adaptive Subnetworks for Heterogeneous Data",
    "url": "http://arxiv.org/abs/2601.22141v1",
    "type": "research"
  }
]